Changelog.txt
LICENSE.txt
MANIFEST.in
Makefile
README.txt
distribute_setup.py
epydoc.css
setup.py
docs/Makefile
docs/source/conf.py
docs/source/index.rst
man/pyzinfomail.1
man/pyzinfomail.html
man/pyzmail.1
man/pyzsendmail.1
man/pyzsendmail.html
pyzmail/__init__.py
pyzmail/generate.py
pyzmail/parse.py
pyzmail/utils.py
pyzmail/version.py
pyzmail.egg-info/PKG-INFO
pyzmail.egg-info/SOURCES.txt
pyzmail.egg-info/dependency_links.txt
pyzmail.egg-info/top_level.txt
pyzmail/tests/__init__.py
pyzmail/tests/test_both.py
pyzmail/tests/test_generate.py
pyzmail/tests/test_parse.py
pyzmail/tests/test_send.py
pyzmail/tests/test_utils.py
scripts/pyzinfomail
scripts/pyzsendmail